jaxued/__init__.py
jaxued/level_sampler.py
jaxued/linen.py
jaxued/utils.py
jaxued/environments/__init__.py
jaxued/environments/underspecified_env.py
jaxued/environments/gymnax/acrobot.py
jaxued/environments/gymnax/cartpole.py
jaxued/environments/gymnax/pendulum.py
jaxued/environments/maze/__init__.py
jaxued/environments/maze/env.py
jaxued/environments/maze/env_editor.py
jaxued/environments/maze/env_solved.py
jaxued/environments/maze/level.py
jaxued/environments/maze/renderer.py
jaxued/environments/maze/util.py
jaxued/wrappers/__init__.py
jaxued/wrappers/autoreplay.py
jaxued/wrappers/autoreset.py
jaxued-0.0.1.dist-info/METADATA
jaxued-0.0.1.dist-info/WHEEL
jaxued-0.0.1.dist-info/top_level.txt
jaxued-0.0.1.dist-info/RECORD
