Metadata-Version: 2.4
Name: jaxued
Version: 0.0.1
Summary: A simple and useable UED library in Jax
Author-email: Samuel Coward <scoward@robots.ox.ac.uk>
Maintainer-email: Samuel Coward <scoward@robots.ox.ac.uk>
License: Apache-2.0
Project-URL: Homepage, https://github.com/dramacow/jaxued
Project-URL: Issues, https://github.com/dramacow/jaxued/issues
Keywords: machine-learning,reinforcement-learning,UED,JAX
Classifier: Programming Language :: Python :: 3
Classifier: Programming Language :: Python :: 3.9
Classifier: Programming Language :: Python :: 3.10
Classifier: Programming Language :: Python :: 3.11
Classifier: Programming Language :: Python :: 3.12
Classifier: Programming Language :: Python :: 3.13
Classifier: License :: OSI Approved :: Apache Software License
Classifier: Operating System :: OS Independent
Classifier: Topic :: Scientific/Engineering
Requires-Python: >=3.9
Requires-Dist: numpy
Requires-Dist: jax
Requires-Dist: flax
Requires-Dist: chex
Requires-Dist: gymnax
Provides-Extra: examples
Requires-Dist: distrax; extra == "examples"
Requires-Dist: optax; extra == "examples"
Requires-Dist: orbax-checkpoint==0.5.3; extra == "examples"
Requires-Dist: orbax; extra == "examples"
Requires-Dist: wandb; extra == "examples"
Requires-Dist: pillow; extra == "examples"
Requires-Dist: imageio; extra == "examples"
Requires-Dist: moviepy; extra == "examples"
